CHANGELOG
LICENSE
MANIFEST.in
README.rst
setup.py
django_system_information.egg-info/PKG-INFO
django_system_information.egg-info/SOURCES.txt
django_system_information.egg-info/dependency_links.txt
django_system_information.egg-info/top_level.txt
systeminformation/__init__.py
systeminformation/urls.py
systeminformation/views.py