Metadata-Version: 1.1
Name: django-system-information
Version: 0.0.11
Summary: A simple Django app to expose some technical information about your application
Home-page: https://charmier@git.epfl.ch/repo/django-system-information.git
Author: Charmier Grégory
Author-email: gregory.charmier@epfl.ch
License: LGPLv3
Platform: UNKNOWN
Classifier: Environment :: Web Environment
Classifier: Framework :: Django
Classifier: Framework :: Django :: 1.8
Classifier: Intended Audience :: Developers
Classifier: License :: OSI Approved :: BSD License
Classifier: Operating System :: OS Independent
Classifier: Programming Language :: Python
Classifier: Programming Language :: Python :: 2.7
Classifier: Topic :: Internet :: WWW/HTTP
Classifier: Topic :: Internet :: WWW/HTTP :: Dynamic Content
